paddingoracle.py
paddingoracle-0.2.2.dist-info/DESCRIPTION.rst
paddingoracle-0.2.2.dist-info/METADATA
paddingoracle-0.2.2.dist-info/metadata.json
paddingoracle-0.2.2.dist-info/pbr.json
paddingoracle-0.2.2.dist-info/RECORD
paddingoracle-0.2.2.dist-info/top_level.txt
paddingoracle-0.2.2.dist-info/WHEEL
