Metadata-Version: 2.0
Name: paddingoracle
Version: 0.2.2
Summary: A portable, padding oracle exploit API
Home-page: https://github.com/mwielgoszewski/python-paddingoracle
Author: Marcin Wielgoszewski
Author-email: marcin.wielgoszewski@gmail.com
License: UNKNOWN
Platform: UNKNOWN
Classifier: License :: OSI Approved :: BSD License
Classifier: Programming Language :: Python
